<?xml version="1.0" encoding="UTF-8" standalone="no"?><sites>
<site><city>San Antonio</city><country>Mexico</country><latitude>19.4805668</latitude><longitude>-99.2058279</longitude></site><site><city>Obudu</city><country>Nigeria</country><latitude>6.6693528</latitude><longitude>9.1622211</longitude></site><site><city>Ad Dawḩah</city><country>Palestinian Territory</country><latitude>31.69948</latitude><longitude>35.18047</longitude></site><site><city>Repušnica</city><country>Croatia</country><latitude>45.4949897</latitude><longitude>16.7305754</longitude></site><site><city>Reuleuet</city><country>Indonesia</country><latitude>5.21667</latitude><longitude>96.28333</longitude></site><site><city>Jaén</city><country>España</country><latitude>37.76922</latitude><longitude>-3.79028</longitude></site></sites>